{"disease":{"_id":{"$oid":"59945363e038e21674ce34c3"},"Createtime":"2017-10-16T14:14:59.190Z","Createuser":"18621723132","Updatetime":"2017-08-16T14:14:59.190Z","Updateuser":"18621723132","PatientID":{"$oid":"59945363e038e21674ce34c2"},"Disease_id":93,"Surgery_id":53,"Surgerymethod":null,"Remark":null,"Fields":[],"doctor_id":262,"user_id":{"$oid":"5992aceafad2131c69da682d"},"disease_name":"心房扑动","surgery_name":"快速性心律失常射频消融术"},"disease_id":"59945363e038e21674ce34c3","patient_id":"59945363e038e21674ce34c2","crf_options":"","select_items":[{"id":"59945363e038e21674ce34c4","name":"知情同意书"},{"id":"59945363e038e21674ce34c5","name":"入院记录"},{"id":"59945363e038e21674ce34c6","name":"病程记录"},{"id":"59945363e038e21674ce34c8","name":"实验室检查"},{"id":"59945363e038e21674ce34c9","name":"其他特殊检查"},{"id":"59945363e038e21674ce34ca","name":"心电图"},{"id":"59945363e038e21674ce34cb","name":"出院记录"},{"id":"599fe5cbfad2132c2cea0131","name":"心肌损伤标记物及NT-proBNP"},{"id":"599fe5cbfad2132c2cea0132","name":"动脉血气分析"},{"id":"599fe5cbfad2132c2cea0133","name":"常规抽血化验"},{"id":"599fe5cbfad2132c2cea0134","name":"胸片"},{"id":"599fe5cbfad2132c2cea0135","name":"心脏彩超"},{"id":"59945363e038e21674ce34c7","name":"术前手术记录","surgery_type":1},{"id":"59945363e038e21674ce34c7","name":"术后手术记录","surgery_type":2},{"id":"59945363e038e21674ce34c7","name":"特殊操作手术记录","surgery_type":3}],"cases":[{"id":"59945363e038e21674ce34c4","name":"知情同意书","is_open":true,"caseresult_json":null,"images":[{"id":"59945cd3e038e21674ce357a","type":"image","surgery_type":null,"surgery_type_name":null,"thumb_url":"https://sqth-api.pointer-health.com/v4/res/CaseImage/59945cd3e038e21674ce357a?t=thumb\u0026ts=636627731843772700\u0026sign=0cbfab09b59360926d4e22da3d080f58","url":"https://sqth-api.pointer-health.com/v4/res/CaseImage/59945cd3e038e21674ce357a?ts=636627731843774600\u0026sign=65b8fbea1f8b1470aa94db3ccc1ed1df","remark":"知情同意书"}],"videos":[]},{"id":"59945363e038e21674ce34c5","name":"入院记录","is_open":true,"caseresult_json":null,"images":[{"id":"59945cc1e038e21674ce3576","type":"image","surgery_type":null,"surgery_type_name":null,"thumb_url":"https://sqth-api.pointer-health.com/v4/res/CaseImage/59945cc1e038e21674ce3576?t=thumb\u0026ts=636627731843777500\u0026sign=34436248ae4e19988d13c24eee59f624","url":"https://sqth-api.pointer-health.com/v4/res/CaseImage/59945cc1e038e21674ce3576?ts=636627731843778700\u0026sign=e5297dd757b1d10603710faa87388159","remark":"入院记录"},{"id":"59945cb7e038e21674ce3573","type":"image","surgery_type":null,"surgery_type_name":null,"thumb_url":"https://sqth-api.pointer-health.com/v4/res/CaseImage/59945cb7e038e21674ce3573?t=thumb\u0026ts=6366277318437800\u0026sign=25e99bead981d348da91ef46e879e85c","url":"https://sqth-api.pointer-health.com/v4/res/CaseImage/59945cb7e038e21674ce3573?ts=636627731843780900\u0026sign=196ebadd8446ff8d5b8e15cb36053e8f","remark":"入院记录"}],"videos":[]},{"id":"59945363e038e21674ce34c6","name":"病程记录","is_open":true,"caseresult_json":null,"images":[{"id":"59945c9de038e21674ce356c","type":"image","surgery_type":null,"surgery_type_name":null,"thumb_url":"https://sqth-api.pointer-health.com/v4/res/CaseImage/59945c9de038e21674ce356c?t=thumb\u0026ts=6366277318437836500\u0026sign=c0fcef35705b448b89afca5f79ba10f7","url":"https://sqth-api.pointer-health.com/v4/res/CaseImage/59945c9de038e21674ce356c?ts=636627731843784500\u0026sign=d09bbf5126429bf806c7d1e32672f003","remark":"病程记录"}],"videos":[]},{"id":"59945363e038e21674ce34c7","name":"手术记录","is_open":false,"caseresult_json":null,"images":[{"id":"59945c84e038e21674ce3565","type":"image","surgery_type":null,"surgery_type_name":null,"thumb_url":"https://sqth-api.pointer-health.com/v4/res/CaseImage/59945c84e038e21674ce3565?t=thumb\u0026ts=636627731843786900\u0026sign=9a4b88a90ca1493cce72da6c4ced2100","url":"https://sqth-api.pointer-health.com/v4/res/CaseImage/59945c84e038e21674ce3565?ts=63662773184378800\u0026sign=bd3edb43d7d66983bd4990546b9e14c8","remark":"手术记录"}],"videos":[]},{"id":"59945363e038e21674ce34c8","name":"实验室检查","is_open":false,"caseresult_json":null,"images":[{"id":"59945c6be038e21674ce355e","type":"image","surgery_type":null,"surgery_type_name":null,"thumb_url":"https://sqth-api.pointer-health.com/v4/res/CaseImage/59945c6be038e21674ce355e?t=thumb\u0026ts=636627731843791500\u0026sign=97f07ba93ad58e0826fb73be026e10c8","url":"https://sqth-api.pointer-health.com/v4/res/CaseImage/59945c6be038e21674ce355e?ts=636627731843792400\u0026sign=99bfb09a7eb2598b854ab5183a4a7e6e","remark":"实验室检查"},{"id":"59945c46e038e21674ce355b","type":"image","surgery_type":null,"surgery_type_name":null,"thumb_url":"https://sqth-api.pointer-health.com/v4/res/CaseImage/59945c46e038e21674ce355b?t=thumb\u0026ts=636627731843796100\u0026sign=405bb5b13f5caddedeedd90f1b9ddc36","url":"https://sqth-api.pointer-health.com/v4/res/CaseImage/59945c46e038e21674ce355b?ts=63662773184379700\u0026sign=7db8e2d83deb145166335c32776d672d","remark":"实验室检查"}],"videos":[]},{"id":"59945363e038e21674ce34c9","name":"其他特殊检查","is_open":true,"caseresult_json":null,"images":[{"id":"59945c39e038e21674ce3557","type":"image","surgery_type":null,"surgery_type_name":null,"thumb_url":"https://sqth-api.pointer-health.com/v4/res/CaseImage/59945c39e038e21674ce3557?t=thumb\u0026ts=6366277318437997400\u0026sign=01ca485abefa0d8459bfa0bbd59c6c00","url":"https://sqth-api.pointer-health.com/v4/res/CaseImage/59945c39e038e21674ce3557?ts=636627731843800900\u0026sign=ef457306f4af42a3438981b1ded74a05","remark":"特殊检查"}],"videos":[]},{"id":"59945363e038e21674ce34ca","name":"心电图","is_open":true,"caseresult_json":null,"images":[{"id":"59945c27e038e21674ce3550","type":"image","surgery_type":null,"surgery_type_name":null,"thumb_url":"https://sqth-api.pointer-health.com/v4/res/CaseImage/59945c27e038e21674ce3550?t=thumb\u0026ts=636627731843805600\u0026sign=70239484b279a27d818358788f9dd32c","url":"https://sqth-api.pointer-health.com/v4/res/CaseImage/59945c27e038e21674ce3550?ts=6366277318438064600\u0026sign=692767c92baf70aa8559159bac4e1039","remark":"心电图"}],"videos":[]},{"id":"59945363e038e21674ce34cb","name":"出院记录","is_open":true,"caseresult_json":null,"images":[{"id":"59945bdfe038e21674ce354c","type":"image","surgery_type":null,"surgery_type_name":null,"thumb_url":"https://sqth-api.pointer-health.com/v4/res/CaseImage/59945bdfe038e21674ce354c?t=thumb\u0026ts=636627731843809300\u0026sign=a57209ccfa17c2ad643d4f92434ddc2c","url":"https://sqth-api.pointer-health.com/v4/res/CaseImage/59945bdfe038e21674ce354c?ts=636627731843810200\u0026sign=a23b0886a9ee06b4e127c3cdb84e357b","remark":"出院记录"},{"id":"59945bd2e038e21674ce3549","type":"image","surgery_type":null,"surgery_type_name":null,"thumb_url":"https://sqth-api.pointer-health.com/v4/res/CaseImage/59945bd2e038e21674ce3549?t=thumb\u0026ts=6366277318438116500\u0026sign=0c45d8ba5b7b38de9f286b715271bb8d","url":"https://sqth-api.pointer-health.com/v4/res/CaseImage/59945bd2e038e21674ce3549?ts=636627731843812600\u0026sign=de3e6ff78b48a0e10404014205faee39","remark":"出院记录"}],"videos":[]},{"id":"599fe5cbfad2132c2cea0131","name":"心肌损伤标记物及NT-proBNP","is_open":false,"caseresult_json":null,"images":[],"videos":[]},{"id":"599fe5cbfad2132c2cea0132","name":"动脉血气分析","is_open":false,"caseresult_json":null,"images":[],"videos":[]},{"id":"599fe5cbfad2132c2cea0133","name":"常规抽血化验","is_open":false,"caseresult_json":null,"images":[],"videos":[]},{"id":"599fe5cbfad2132c2cea0134","name":"胸片","is_open":false,"caseresult_json":null,"images":[],"videos":[]},{"id":"599fe5cbfad2132c2cea0135","name":"心脏彩超","is_open":false,"caseresult_json":null,"images":[],"videos":[]}],"uncategorized":{"doctor_files":[],"patient_files":[]},"ae_list":[]}
